LICENSE.md
MANIFEST.in
README.md
setup.py
appthwack/__init__.py
appthwack/appthwack.py
appthwack.egg-info/PKG-INFO
appthwack.egg-info/SOURCES.txt
appthwack.egg-info/dependency_links.txt
appthwack.egg-info/requires.txt
appthwack.egg-info/top_level.txt