Metadata-Version: 1.1
Name: appthwack
Version: 1.0.0
Summary: AppThwack python client
Home-page: https://github.com/appthwack/appthwack-python
Author: Andrew Hawker
Author-email: andrew@appthwack.com
License: The MIT License (MIT)
